setup.py
bigfoot/__init__.py
bigfoot/elements.py
bigfoot/utils.py
django_bigfoot.egg-info/PKG-INFO
django_bigfoot.egg-info/SOURCES.txt
django_bigfoot.egg-info/dependency_links.txt
django_bigfoot.egg-info/requires.txt
django_bigfoot.egg-info/top_level.txt