Metadata-Version: 1.0
Name: django-bigfoot
Version: 0.2
Summary: A Django library for defining HTML building blocks (e.g., forms, form fields, tables) that can be easily rendered into HTML.
Home-page: https://github.com/setaris/django-bigfoot
Author: Setaris
Author-email: support@setaris.com
License: UNKNOWN
Platform: UNKNOWN
